pywkdb/__init__.py
pywkdb/db/__init__.py
pywkdb/db/db_mssql.py
pywkdb/db/db_mysql.py
pywkdb/db/db_oraclel.py
pywkdb/db/db_sqlite.py
pywkdb/utils/__init__.py
pywkdb/utils/db_base.py
pywkdb/utils/db_conn.py
pywkdb/utils/db_utils.py
pywkdb/utils/sql_builder.py
pywkdb/utils/url_parse.py
Pywkdb-1.0.8.dist-info/METADATA
Pywkdb-1.0.8.dist-info/WHEEL
Pywkdb-1.0.8.dist-info/top_level.txt
Pywkdb-1.0.8.dist-info/RECORD
